spotifycodegen/__init__.py
spotifycodegen/cli.py
spotifycodegen/main.py
spotifycodegen/py.typed
spotify_codegen-0.4.0.dist-info/LICENSE
spotify_codegen-0.4.0.dist-info/METADATA
spotify_codegen-0.4.0.dist-info/WHEEL
spotify_codegen-0.4.0.dist-info/entry_points.txt
spotify_codegen-0.4.0.dist-info/RECORD
