Metadata-Version: 2.1
Name: spotify-codegen
Version: 0.4.0
Summary: spotify-codegen
Home-page: https://github.com/tilschuenemann/spotify-codegen
License: MIT
Keywords: spotify-codegen,spoticode,spotify,spotipy,art,code,qr,album,track,song,album,generator
Author: Til Schünemann
Author-email: til.schuenemann@mailbox.org
Requires-Python: >=3.10,<4.0
Classifier: Development Status :: 3 - Alpha
Classifier: License :: OSI Approved :: MIT License
Classifier: Programming Language :: Python :: 3
Classifier: Programming Language :: Python :: 3.10
Classifier: Programming Language :: Python :: 3.11
Classifier: Programming Language :: Python :: 3.12
Requires-Dist: click (>=8.0.1)
Requires-Dist: colorthief (>=0.2.1,<0.3.0)
Requires-Dist: pillow (>=10.4.0,<11.0.0)
Requires-Dist: spotipy (>=2.21.0,<3.0.0)
Requires-Dist: tqdm (>=4.64.1,<5.0.0)
Project-URL: Changelog, https://github.com/tilschuenemann/spotify-codegen/releases
Project-URL: Documentation, https://spotify-codegen.readthedocs.io
Project-URL: Repository, https://github.com/tilschuenemann/spotify-codegen
